sleet/__init__.py
sleet/cli.py
sleet/taskmaster.py
sleet/libs/__init__.py
sleet/libs/configloader.py
sleet/libs/constants.py
sleet/libs/logformatter.py
sleet/libs/registry.py
sleet/modules/builtins/__init__.py
sleet/modules/builtins/command.py
sleet/modules/builtins/file.py
sleet/modules/builtins/git.py
sleet/modules/builtins/uv.py
sleet/modules/helpers/__init__.py
sleet/modules/helpers/command.py
sleet-0.1.0.dist-info/METADATA
sleet-0.1.0.dist-info/WHEEL
sleet-0.1.0.dist-info/entry_points.txt
sleet-0.1.0.dist-info/top_level.txt
sleet-0.1.0.dist-info/RECORD
