Metadata-Version: 2.4
Name: sleet
Version: 0.1.0
Summary: Add your description here
Requires-Python: >=3.12
Requires-Dist: platformdirs>=4.5.0
Requires-Dist: pyyaml>=6.0.3
Requires-Dist: termcolor>=3.2.0
Requires-Dist: typer>=0.20.0
